dazzl_aws_lambda_tools
