Metadata-Version: 2.1
Name: dazzl-aws-lambda-tools
Version: 0.3
Summary: Library python for simplify to create lambda function (AWS lambda) and Dazzl API service.
Home-page: http://github.com/dazzl-tv/dazzl-aws-lambda-tools.git
Author: VAILLANT Jeremy
Author-email: jeremy@dazzl.tv
License: UNKNOWN
Platform: UNKNOWN
Classifier: Programming Language :: Python :: 3
Classifier: License :: OSI Approved :: MIT License
Classifier: Intended Audience :: Developers
Classifier: Operating System :: OS Independent
